__init__.py
redis_rw_lock/__init__.py
redis_rw_lock-1.0.6.dist-info/DESCRIPTION.rst
redis_rw_lock-1.0.6.dist-info/METADATA
redis_rw_lock-1.0.6.dist-info/metadata.json
redis_rw_lock-1.0.6.dist-info/RECORD
redis_rw_lock-1.0.6.dist-info/top_level.txt
redis_rw_lock-1.0.6.dist-info/WHEEL
